gfwlist-0.2.0.dist-info/METADATA
gfwlist-0.2.0.dist-info/WHEEL
gfwlist/__init__.py
gfwlist/__init__.pyi
gfwlist/py.typed
gfwlist/gfwlist.cpython-312-x86_64-linux-gnu.so
gfwlist-0.2.0.dist-info/RECORD
