Metadata-Version: 2.4
Name: gfwlist
Version: 0.2.0
Classifier: Programming Language :: Rust
Classifier: Programming Language :: Python :: Implementation :: CPython
Classifier: Programming Language :: Python :: Implementation :: PyPy
Classifier: License :: OSI Approved :: MIT License
Summary: A GFW list parser and matcher.
Author-email: Shigma <shigma10826@gmail.com>
License: MIT
Requires-Python: >=3.8
Project-URL: Homepage, https://github.com/shigma/gfwlist
Project-URL: Repository, https://github.com/shigma/gfwlist.git
